whatsapp/__init__.py
whatsapp/constants.py
whatsapp/ext/_buttons.py
whatsapp/ext/_media.py
whatsapp/ext/_message.py
whatsapp/ext/_property.py
whatsapp/ext/_send_media.py
whatsapp/ext/_send_others.py
whatsapp/ext/_static.py
whatsapp_python_cloud_api-3.2.5.dist-info/METADATA
whatsapp_python_cloud_api-3.2.5.dist-info/WHEEL
whatsapp_python_cloud_api-3.2.5.dist-info/licenses/LICENSE
whatsapp_python_cloud_api-3.2.5.dist-info/RECORD
