Metadata-Version: 2.3
Name: whatsapp-python-cloud-api
Version: 3.2.5
Summary: Open source Python wrapper for the WhatsApp Cloud API
Project-URL: Homepage, https://github.com/yoandresaav/whatsapp-python-cloud-api
Project-URL: Docs, https://github.com/yoandresaav/whatsapp-python-cloud-api/wiki
Project-URL: Issues Reporting, https://github.com/yoandresaav/whatsapp-python-cloud-api/issues
Project-URL: Download, https://github.com/yoandresaav/whatsapp-python-cloud-api/releases/latest
Project-URL: Changelog, https://github.com/yoandresaav/whatsapp-python-cloud-api/releases
Author-email: Yoandre Saavedra <mail@example.com>
License-File: LICENSE
Classifier: Development Status :: 4 - Beta
Classifier: Intended Audience :: Customer Service
Classifier: Intended Audience :: Developers
Classifier: Intended Audience :: Education
Classifier: Intended Audience :: Telecommunications Industry
Classifier: License :: OSI Approved :: MIT License
Classifier: Programming Language :: Python :: 3.10
Classifier: Programming Language :: Python :: 3.11
Classifier: Programming Language :: Python :: 3.12
Classifier: Programming Language :: Python :: 3.13
Classifier: Programming Language :: Python :: 3.14
Classifier: Topic :: Communications :: Chat
Classifier: Topic :: Communications :: Telephony
Classifier: Topic :: Internet :: WWW/HTTP :: HTTP Servers
Classifier: Topic :: Internet :: WWW/HTTP :: WSGI :: Application
Classifier: Topic :: Software Development :: Build Tools
Classifier: Topic :: Software Development :: Libraries :: Python Modules
Requires-Python: >=3.10
Requires-Dist: python-dotenv
Requires-Dist: requests
Requires-Dist: requests-toolbelt
